setup.py
DataSBI/Binomialdistribution.py
DataSBI/Clothing.py
DataSBI/Gaussiandistribution.py
DataSBI/Generaldistribution.py
DataSBI/SalesPerson.py
DataSBI/__init__.py
DataSBI/test1oneobject.py
DataSBI/test2multiobj.py
DataSBI/test3.py
DataSBI/test4.py
DataSBI/testdistributions.py
DataScienceBI.egg-info/PKG-INFO
DataScienceBI.egg-info/SOURCES.txt
DataScienceBI.egg-info/dependency_links.txt
DataScienceBI.egg-info/not-zip-safe
DataScienceBI.egg-info/top_level.txt