Metadata-Version: 1.0
Name: DataScienceBI
Version: 0.2
Summary: Data Science for Bussiness Intelligence
Home-page: UNKNOWN
Author: T.T. Pham
Author-email: zeniththuy@gmail.com
License: UNKNOWN
Platform: UNKNOWN
